ai_resume_parser-1.0.6.dist-info/licenses/LICENSE
resumeparser_pro/__init__.py
resumeparser_pro/extractors.py
resumeparser_pro/models.py
resumeparser_pro/parser.py
resumeparser_pro/utils.py
tests/__init__.py
tests/test_parser.py
ai_resume_parser-1.0.6.dist-info/METADATA
ai_resume_parser-1.0.6.dist-info/WHEEL
ai_resume_parser-1.0.6.dist-info/top_level.txt
ai_resume_parser-1.0.6.dist-info/RECORD
