Metadata-Version: 2.4
Name: ai-resume-parser
Version: 1.0.6
Summary: AI-powered resume parser with parallel processing for multiple file formats (PDF, DOCX, images, etc.)
Author-email: Ruthik Reddy <ruthikr369@gmail.com>
License-Expression: MIT
Project-URL: Homepage, https://github.com/Ruthikr
Project-URL: Repository, https://github.com/Ruthikr/ai-resume-parser
Project-URL: Documentation, https://github.com/Ruthikr/ai-resume-parser/tree/main/docs
Project-URL: Issues, https://github.com/Ruthikr/ai-resume-parser/issues
Keywords: resume parsing,AI,NLP,OCR,parallel processing,recruitment,HR,LLM,resume,parser,Gemini,OpenAI,job
Classifier: Development Status :: 5 - Production/Stable
Classifier: Intended Audience :: Developers
Classifier: Programming Language :: Python :: 3
Classifier: Programming Language :: Python :: 3.8
Classifier: Programming Language :: Python :: 3.9
Classifier: Programming Language :: Python :: 3.10
Classifier: Programming Language :: Python :: 3.11
Classifier: Topic :: Scientific/Engineering :: Artificial Intelligence
Classifier: Topic :: Software Development :: Libraries :: Python Modules
Classifier: Topic :: Text Processing :: Linguistic
Requires-Python: >=3.8
License-File: LICENSE
Requires-Dist: pydantic>=2.0.0
Requires-Dist: langchain-core>=0.1.0
Requires-Dist: python-dateutil>=2.8.0
Requires-Dist: pdfminer.six>=20221105
Requires-Dist: python-docx>=0.8.11
Requires-Dist: PyMuPDF>=1.23.0
Requires-Dist: phonenumbers>=8.13.0
Requires-Dist: email-validator>=2.2.0
Provides-Extra: ocr
Requires-Dist: pytesseract>=0.3.10; extra == "ocr"
Requires-Dist: Pillow>=9.0.0; extra == "ocr"
Provides-Extra: html
Requires-Dist: beautifulsoup4>=4.11.1; extra == "html"
Provides-Extra: odt
Requires-Dist: odfpy>=1.4.1; extra == "odt"
Provides-Extra: full
Requires-Dist: pytesseract>=0.3.10; extra == "full"
Requires-Dist: Pillow>=9.0.0; extra == "full"
Requires-Dist: beautifulsoup4>=4.11.1; extra == "full"
Requires-Dist: odfpy>=1.4.1; extra == "full"
Provides-Extra: dev
Requires-Dist: pytest>=7.0.0; extra == "dev"
Requires-Dist: black>=22.0.0; extra == "dev"
Requires-Dist: flake8>=4.0.0; extra == "dev"
Requires-Dist: mypy>=0.950; extra == "dev"
Dynamic: license-file
Dynamic: requires-python
